causal_forecast/__init__.py
causal_forecast/causal_forecast.py
causal_forecast/cli.py
causal_forecast-0.0.4.dist-info/METADATA
causal_forecast-0.0.4.dist-info/WHEEL
causal_forecast-0.0.4.dist-info/entry_points.txt
causal_forecast-0.0.4.dist-info/top_level.txt
causal_forecast-0.0.4.dist-info/RECORD
