Metadata-Version: 2.2
Name: causal_forecast
Version: 0.0.4
Summary: Get the causal_forecast analysis
Home-page: https://github.com/A284viral/causal_forecast
Author: Aviral Srivastava
Author-email: aviralsrivastava284@gmail.com
Classifier: Programming Language :: Python :: 3
Classifier: License :: OSI Approved :: MIT License
Classifier: Operating System :: OS Independent
Requires-Python: >=3.6
Requires-Dist: absl-py==2.2.1
Requires-Dist: altair==5.5.0
Requires-Dist: anyio==4.9.0
Requires-Dist: argon2-cffi==23.1.0
Requires-Dist: argon2-cffi-bindings==21.2.0
Requires-Dist: arrow==1.3.0
Requires-Dist: asttokens==3.0.0
Requires-Dist: astunparse==1.6.3
Requires-Dist: async-lru==2.0.5
Requires-Dist: attrs==25.3.0
Requires-Dist: babel==2.17.0
Requires-Dist: beautifulsoup4==4.13.3
Requires-Dist: bleach==6.2.0
Requires-Dist: blinker==1.9.0
Requires-Dist: boto3==1.37.35
Requires-Dist: botocore==1.37.35
Requires-Dist: cachetools==5.5.2
Requires-Dist: catboost==1.2.8
Requires-Dist: certifi==2025.1.31
Requires-Dist: cffi==1.17.1
Requires-Dist: charset-normalizer==3.4.1
Requires-Dist: click==8.2.0
Requires-Dist: cloudpickle==3.1.1
Requires-Dist: cmdstanpy==1.2.5
Requires-Dist: colorama==0.4.6
Requires-Dist: comm==0.2.2
Requires-Dist: contourpy==1.3.1
Requires-Dist: copulas==0.12.2
Requires-Dist: cryptography==44.0.2
Requires-Dist: ctgan==0.11.0
Requires-Dist: cycler==0.12.1
Requires-Dist: Cython==3.0.12
Requires-Dist: debugpy==1.8.13
Requires-Dist: decorator==5.2.1
Requires-Dist: deepecho==0.7.0
Requires-Dist: defusedxml==0.7.1
Requires-Dist: easyocr==1.7.2
Requires-Dist: et_xmlfile==2.0.0
Requires-Dist: executing==2.2.0
Requires-Dist: Faker==37.1.0
Requires-Dist: fastjsonschema==2.21.1
Requires-Dist: filelock==3.18.0
Requires-Dist: FLAML==2.3.4
Requires-Dist: flatbuffers==25.2.10
Requires-Dist: fonttools==4.56.0
Requires-Dist: fqdn==1.5.1
Requires-Dist: fsspec==2025.3.2
Requires-Dist: gast==0.6.0
Requires-Dist: gitdb==4.0.12
Requires-Dist: GitPython==3.1.44
Requires-Dist: google-pasta==0.2.0
Requires-Dist: gplearn==0.4.2
Requires-Dist: graphviz==0.20.3
Requires-Dist: grpcio==1.71.0
Requires-Dist: h11==0.14.0
Requires-Dist: h2o==3.46.0.7
Requires-Dist: h5py==3.13.0
Requires-Dist: holidays==0.69
Requires-Dist: httpcore==1.0.7
Requires-Dist: httpx==0.28.1
Requires-Dist: idna==3.10
Requires-Dist: imageio==2.37.0
Requires-Dist: imodels==2.0.0
Requires-Dist: importlib_resources==6.5.2
Requires-Dist: ipykernel==6.29.5
Requires-Dist: ipython==9.0.2
Requires-Dist: ipython_pygments_lexers==1.1.1
Requires-Dist: ipywidgets==8.1.5
Requires-Dist: isoduration==20.11.0
Requires-Dist: jedi==0.19.2
Requires-Dist: Jinja2==3.1.6
Requires-Dist: jmespath==1.0.1
Requires-Dist: joblib==1.4.2
Requires-Dist: json5==0.10.0
Requires-Dist: jsonpointer==3.0.0
Requires-Dist: jsonschema==4.23.0
Requires-Dist: jsonschema-specifications==2024.10.1
Requires-Dist: jupyter==1.1.1
Requires-Dist: jupyter-console==6.6.3
Requires-Dist: jupyter-events==0.12.0
Requires-Dist: jupyter-lsp==2.2.5
Requires-Dist: jupyter_client==8.6.3
Requires-Dist: jupyter_core==5.7.2
Requires-Dist: jupyter_server==2.15.0
Requires-Dist: jupyter_server_terminals==0.5.3
Requires-Dist: jupyterlab==4.3.6
Requires-Dist: jupyterlab_pygments==0.3.0
Requires-Dist: jupyterlab_server==2.27.3
Requires-Dist: jupyterlab_widgets==3.0.13
Requires-Dist: keras==3.9.1
Requires-Dist: kiwisolver==1.4.8
Requires-Dist: lazy_loader==0.4
Requires-Dist: libclang==18.1.1
Requires-Dist: lightgbm==4.6.0
Requires-Dist: llvmlite==0.44.0
Requires-Dist: lxml==5.3.2
Requires-Dist: Markdown==3.7
Requires-Dist: markdown-it-py==3.0.0
Requires-Dist: MarkupSafe==3.0.2
Requires-Dist: matplotlib==3.10.1
Requires-Dist: matplotlib-inline==0.1.7
Requires-Dist: mdurl==0.1.2
Requires-Dist: mistune==3.1.2
Requires-Dist: ml_dtypes==0.5.1
Requires-Dist: mlxtend==0.23.4
Requires-Dist: mpmath==1.3.0
Requires-Dist: namex==0.0.8
Requires-Dist: narwhals==1.35.0
Requires-Dist: nbclient==0.10.2
Requires-Dist: nbconvert==7.16.6
Requires-Dist: nbformat==5.10.4
Requires-Dist: nest-asyncio==1.6.0
Requires-Dist: networkx==3.4.2
Requires-Dist: ninja==1.11.1.4
Requires-Dist: notebook==7.3.3
Requires-Dist: notebook_shim==0.2.4
Requires-Dist: numba==0.61.2
Requires-Dist: numpy==1.26.4
Requires-Dist: opencv-python==4.11.0.86
Requires-Dist: opencv-python-headless==4.11.0.86
Requires-Dist: openpyxl==3.1.5
Requires-Dist: opt_einsum==3.4.0
Requires-Dist: optree==0.14.1
Requires-Dist: overrides==7.7.0
Requires-Dist: packaging==24.2
Requires-Dist: pandas==2.2.3
Requires-Dist: pandocfilters==1.5.1
Requires-Dist: parso==0.8.4
Requires-Dist: patsy==1.0.1
Requires-Dist: pdf2image==1.17.0
Requires-Dist: pdfminer.six==20250327
Requires-Dist: pdfplumber==0.11.6
Requires-Dist: pillow==11.1.0
Requires-Dist: platformdirs==4.3.6
Requires-Dist: plotly==6.0.1
Requires-Dist: pmdarima==2.0.4
Requires-Dist: progressbar2==4.5.0
Requires-Dist: prometheus_client==0.21.1
Requires-Dist: prompt_toolkit==3.0.50
Requires-Dist: prophet==1.1.6
Requires-Dist: protobuf==5.29.4
Requires-Dist: psutil==7.0.0
Requires-Dist: pure_eval==0.2.3
Requires-Dist: pyarrow==20.0.0
Requires-Dist: pyclipper==1.3.0.post6
Requires-Dist: pycparser==2.22
Requires-Dist: pydeck==0.9.1
Requires-Dist: pygam==0.9.1
Requires-Dist: Pygments==2.19.1
Requires-Dist: pyparsing==3.2.1
Requires-Dist: pypdfium2==4.30.1
Requires-Dist: python-bidi==0.6.6
Requires-Dist: python-dateutil==2.9.0.post0
Requires-Dist: python-json-logger==3.3.0
Requires-Dist: python-utils==3.9.1
Requires-Dist: pytorch-tabnet==4.1.0
Requires-Dist: pytz==2025.1
Requires-Dist: pywin32==310
Requires-Dist: pywinpty==2.0.15
Requires-Dist: PyYAML==6.0.2
Requires-Dist: pyzmq==26.3.0
Requires-Dist: rdt==1.16.0
Requires-Dist: referencing==0.36.2
Requires-Dist: requests==2.32.3
Requires-Dist: rfc3339-validator==0.1.4
Requires-Dist: rfc3986-validator==0.1.1
Requires-Dist: rich==13.9.4
Requires-Dist: rpds-py==0.23.1
Requires-Dist: s3transfer==0.11.4
Requires-Dist: scikit-image==0.25.2
Requires-Dist: scikit-learn==1.6.1
Requires-Dist: scipy==1.11.4
Requires-Dist: sdmetrics==0.20.1
Requires-Dist: sdv==1.20.0
Requires-Dist: seaborn==0.13.2
Requires-Dist: Send2Trash==1.8.3
Requires-Dist: shap==0.47.2
Requires-Dist: shapely==2.1.0
Requires-Dist: six==1.17.0
Requires-Dist: slicer==0.0.8
Requires-Dist: smmap==5.0.2
Requires-Dist: sniffio==1.3.1
Requires-Dist: soupsieve==2.6
Requires-Dist: stack-data==0.6.3
Requires-Dist: stanio==0.5.1
Requires-Dist: statsmodels==0.14.4
Requires-Dist: streamlit==1.45.0
Requires-Dist: sympy==1.13.1
Requires-Dist: tabulate==0.9.0
Requires-Dist: tenacity==9.1.2
Requires-Dist: tensorboard==2.19.0
Requires-Dist: tensorboard-data-server==0.7.2
Requires-Dist: tensorflow==2.19.0
Requires-Dist: tensorflow-io-gcs-filesystem==0.31.0
Requires-Dist: termcolor==2.5.0
Requires-Dist: terminado==0.18.1
Requires-Dist: threadpoolctl==3.6.0
Requires-Dist: tifffile==2025.3.30
Requires-Dist: tinycss2==1.4.0
Requires-Dist: toml==0.10.2
Requires-Dist: torch==2.6.0
Requires-Dist: torchaudio==2.6.0
Requires-Dist: torchvision==0.21.0
Requires-Dist: tornado==6.4.2
Requires-Dist: tqdm==4.67.1
Requires-Dist: traitlets==5.14.3
Requires-Dist: types-python-dateutil==2.9.0.20241206
Requires-Dist: typing_extensions==4.12.2
Requires-Dist: tzdata==2025.1
Requires-Dist: uri-template==1.3.0
Requires-Dist: urllib3==2.3.0
Requires-Dist: watchdog==6.0.0
Requires-Dist: wcwidth==0.2.13
Requires-Dist: webcolors==24.11.1
Requires-Dist: webencodings==0.5.1
Requires-Dist: websocket-client==1.8.0
Requires-Dist: Werkzeug==3.1.3
Requires-Dist: widgetsnbextension==4.0.13
Requires-Dist: wrapt==1.17.2
Requires-Dist: xgboost==3.0.0
Requires-Dist: xlrd==2.0.1
Requires-Dist: XlsxWriter==3.2.2
Dynamic: author
Dynamic: author-email
Dynamic: classifier
Dynamic: description-content-type
Dynamic: home-page
Dynamic: requires-dist
Dynamic: requires-python
Dynamic: summary
